Metadata-Version: 1.1
Name: scodb
Version: 1.0
Summary: Conector escrito em python para API do SCODB.
Home-page: https://github.com/Otoru/scodb
Author: Vitor Hugo de O. Vargas
Author-email: vitor.hov@gmail.com
License: MIT
Keywords: Demolay,SCODB
Platform: UNKNOWN
Classifier: Development Status :: 5 - Production/Stable
Classifier: Environment :: Plugins
Classifier: Intended Audience :: Developers
Classifier: License :: OSI Approved :: MIT License
Classifier: Natural Language :: Portuguese (Brazilian)
Classifier: Operating System :: OS Independent
Classifier: Programming Language :: Python :: 3.7
Classifier: Topic :: Utilities
